Shakersynth-0.7.4.data/scripts/shakersynth.bat
shakersynth/Shakersynth.lua
shakersynth/__init__.py
shakersynth/__main__.py
shakersynth/aircraft/__init__.py
shakersynth/aircraft/aircraft.py
shakersynth/config/__init__.py
shakersynth/config/loader.py
shakersynth/receiver/__init__.py
shakersynth/receiver/shakersynth.py
shakersynth/synth/__init__.py
shakersynth/synth/rotor.py
Shakersynth-0.7.4.dist-info/LICENSE
Shakersynth-0.7.4.dist-info/METADATA
Shakersynth-0.7.4.dist-info/WHEEL
Shakersynth-0.7.4.dist-info/top_level.txt
Shakersynth-0.7.4.dist-info/RECORD
