Metadata-Version: 2.1
Name: Shakersynth
Version: 0.7.4
Summary: Bass shaker synthesizer for DCS World.
Home-page: https://github.com/jarpy/shakersynth
Author: Toby McLaughlin
Author-email: toby@jarpy.net
License: UNKNOWN
Platform: UNKNOWN
Classifier: Development Status :: 3 - Alpha
Classifier: Environment :: Console
Classifier: Intended Audience :: End Users/Desktop
Classifier: License :: OSI Approved :: MIT License
Classifier: Natural Language :: English
Classifier: Operating System :: OS Independent
Classifier: Programming Language :: Python :: 3
Classifier: Programming Language :: Python :: 3.7
Classifier: Programming Language :: Python :: 3.8
Classifier: Topic :: Games/Entertainment :: Simulation
Classifier: Topic :: Multimedia :: Sound/Audio :: Sound Synthesis
Requires-Python: >=3.7
License-File: LICENSE
Requires-Dist: func-timeout
Requires-Dist: python-configuration[yaml]
Requires-Dist: pyo
Requires-Dist: pyaml
Requires-Dist: wxPython
